{"trial_n":5,"sid":"A26FIQ42LD6QIO","expt":"live","phase":"feedback","error_threshold":0.4,"responses":[{"type":"circle","center":{"x":0.081666666666667,"y":-0.023333333333333,"distance":0.084934615374939,"angle":-15.945395900923},"radius":0.03,"color":"#4cbf40","border":{"width":0.005,"color":"#000000"}},{"type":"circle","center":{"x":0.625,"y":0.34333333333333,"distance":0.71309380713745,"angle":28.781459432863},"radius":0.03,"color":"#404cbf","border":{"width":0.005,"color":"#000000"}},{"type":"circle","center":{"x":-0.135,"y":0.31,"distance":0.33811980125393,"angle":113.5323485609},"radius":0.03,"color":"#bf404d","border":{"width":0.005,"color":"#000000"}},{"type":"circle","center":{"x":0.061666666666667,"y":-0.28333333333333,"distance":0.28996647315777,"angle":-77.721234629037},"radius":0.03,"color":"#4cbf40","border":{"width":0.005,"color":"#000000"}},{"type":"circle","center":{"x":0.705,"y":0.57333333333333,"distance":0.90870023171072,"angle":39.119346330951},"radius":0.03,"color":"#404cbf","border":{"width":0.005,"color":"#000000"}},{"type":"circle","center":{"x":-0.235,"y":0.44333333333333,"distance":0.50176632454206,"angle":117.92695283429},"radius":0.03,"color":"#bf404d","border":{"width":0.005,"color":"#000000"}},{"type":"circle","center":{"x":-0.075,"y":-0.11,"distance":0.13313526955694,"angle":-124.28687697721},"radius":0.03,"color":"#4cbf40","border":{"width":0.005,"color":"#000000"}},{"type":"circle","center":{"x":0.545,"y":0.65333333333333,"distance":0.85080517419938,"angle":50.165687611167},"radius":0.03,"color":"#404cbf","border":{"width":0.005,"color":"#000000"}},{"type":"circle","center":{"x":-0.37166666666667,"y":0.35333333333333,"distance":0.5128162980596,"angle":136.44855008628},"radius":0.03,"color":"#bf404d","border":{"width":0.005,"color":"#000000"}},{"type":"circle","center":{"x":-0.21166666666667,"y":-0.33666666666667,"distance":0.39767728401585,"angle":-122.15810371583},"radius":0.03,"color":"#4cbf40","border":{"width":0.005,"color":"#000000"}},{"type":"circle","center":{"x":0.55166666666667,"y":0.47,"distance":0.72473175114046,"angle":40.429793696945},"radius":0.03,"color":"#404cbf","border":{"width":0.005,"color":"#000000"}},{"type":"circle","center":{"x":-0.54166666666667,"y":0.23333333333333,"distance":0.58978574264068,"angle":156.6951094608},"radius":0.03,"color":"#bf404d","border":{"width":0.005,"color":"#000000"}},{"type":"circle","center":{"x":-0.30833333333333,"y":-0.16,"distance":0.34737507746591,"angle":-152.57434733309},"radius":0.03,"color":"#4cbf40","border":{"width":0.005,"color":"#000000"}},{"type":"circle","center":{"x":0.78833333333333,"y":0.32333333333333,"distance":0.85206448634413,"angle":22.300887827925},"radius":0.03,"color":"#404cbf","border":{"width":0.005,"color":"#000000"}},{"type":"circle","center":{"x":-0.48833333333333,"y":0.1,"distance":0.49846709464562,"angle":168.42707235232},"radius":0.03,"color":"#bf404d","border":{"width":0.005,"color":"#000000"}}],"state":{"nReported":15,"selected":null,"start":"2018-04-21T03:12:28.821Z","reporting":null,"displayTime":0},"stimuli":[{"type":"circle","center":{"x":-0.061666666666667,"y":-0.16333333333333,"distance":0.17458681380779,"angle":-110.68408026795},"radius":0.03,"color":"#4cbf40","border":{"width":0.005,"color":"#000000"}},{"type":"circle","center":{"x":0.59166666666667,"y":0.59,"distance":0.8355653442098,"angle":44.919187952723},"radius":0.03,"color":"#404cbf","border":{"width":0.005,"color":"#000000"}},{"type":"circle","center":{"x":-0.23833333333333,"y":0.11333333333333,"distance":0.2639076016757,"angle":154.56776858129},"radius":0.03,"color":"#bf404d","border":{"width":0.005,"color":"#000000"}},{"type":"circle","center":{"x":-0.085,"y":-0.38666666666667,"distance":0.39589911734066,"angle":-102.39799565445},"radius":0.03,"color":"#4cbf40","border":{"width":0.005,"color":"#000000"}},{"type":"circle","center":{"x":0.55166666666667,"y":0.39666666666667,"distance":0.67947079080381,"angle":35.71739022648},"radius":0.03,"color":"#404cbf","border":{"width":0.005,"color":"#000000"}},{"type":"circle","center":{"x":-0.32833333333333,"y":0.25666666666667,"distance":0.41674999166833,"angle":141.98433951598},"radius":0.03,"color":"#bf404d","border":{"width":0.005,"color":"#000000"}},{"type":"circle","center":{"x":-0.21833333333333,"y":-0.21333333333333,"distance":0.30525490259053,"angle":-135.66362800001},"radius":0.03,"color":"#4cbf40","border":{"width":0.005,"color":"#000000"}},{"type":"circle","center":{"x":0.405,"y":0.50666666666667,"distance":0.64864174326905,"angle":51.363183630516},"radius":0.03,"color":"#404cbf","border":{"width":0.005,"color":"#000000"}},{"type":"circle","center":{"x":-0.49166666666667,"y":0.18666666666667,"distance":0.52590926551598,"angle":159.21018249654},"radius":0.03,"color":"#bf404d","border":{"width":0.005,"color":"#000000"}},{"type":"circle","center":{"x":-0.345,"y":-0.43,"distance":0.55129393248974,"angle":-128.74096369488},"radius":0.03,"color":"#4cbf40","border":{"width":0.005,"color":"#000000"}},{"type":"circle","center":{"x":0.68833333333333,"y":0.38,"distance":0.78625872190888,"angle":28.901249486146},"radius":0.03,"color":"#404cbf","border":{"width":0.005,"color":"#000000"}},{"type":"circle","center":{"x":-0.60166666666667,"y":-0.0033333333333333,"distance":0.60167590020616,"angle":-179.68257510625},"radius":0.03,"color":"#bf404d","border":{"width":0.005,"color":"#000000"}},{"type":"circle","center":{"x":-0.455,"y":-0.21,"distance":0.50112373721467,"angle":-155.22485943117},"radius":0.03,"color":"#4cbf40","border":{"width":0.005,"color":"#000000"}},{"type":"circle","center":{"x":0.45166666666667,"y":0.69333333333333,"distance":0.8274744037666,"angle":56.918077127235},"radius":0.03,"color":"#404cbf","border":{"width":0.005,"color":"#000000"}},{"type":"circle","center":{"x":-0.64833333333333,"y":0.13333333333333,"distance":0.66190172147298,"angle":168.37883425406},"radius":0.03,"color":"#bf404d","border":{"width":0.005,"color":"#000000"}}],"seed":1,"chain":0,"iter":25,"settings":{"name":"live","maxTrials":10,"debug":false,"error_threshold":0.4,"error_match":"color","readURL":"request.php","saveURL":"submit.php","timing":{"consent":null,"instructions":null,"presentation":15000,"mask":1000,"response":null,"feedback":null},"default":{"n":15,"practice":[3,9],"colors":[0,0.333,0.666],"coffset":0.317,"type":"circle","environment":{"type":"circle","center":{"x":0,"y":0},"radius":0.95,"color":"#FFFFFF","border":{"width":0.01,"color":"#888888"}},"circle":{"type":"circle","center":{"x":null,"y":null},"radius":0.03,"color":"#333333","border":{"width":0.005,"color":"#000000"}},"response":{"xy":true,"angle":false,"color":false,"size":false,"aspect_ratio":false}}},"error":0.15885915651021,"score":60,"submit_time":"2018-04-20 20:13:39"}