{"trial_n":8,"sid":"A2PVZXYJSDD9X1","expt":"live","phase":"feedback","error_threshold":0.4,"responses":[{"type":"circle","center":{"x":0.55,"y":-0.10333333333333,"distance":0.55962288889732,"angle":-10.640619702411},"radius":0.03,"color":"#4cbf40","border":{"width":0.005,"color":"#000000"}},{"type":"circle","center":{"x":-0.52666666666667,"y":0.026666666666667,"distance":0.52734134001507,"angle":177.10142320072},"radius":0.03,"color":"#404cbf","border":{"width":0.005,"color":"#000000"}},{"type":"circle","center":{"x":0.46666666666667,"y":0.17666666666667,"distance":0.49898786447056,"angle":20.735233937997},"radius":0.03,"color":"#bf404d","border":{"width":0.005,"color":"#000000"}},{"type":"circle","center":{"x":-0.53,"y":0.14,"distance":0.54817880294663,"angle":165.20323775494},"radius":0.03,"color":"#4cbf40","border":{"width":0.005,"color":"#000000"}},{"type":"circle","center":{"x":-0.15666666666667,"y":-0.47333333333333,"distance":0.49858689201471,"angle":-108.31381627715},"radius":0.03,"color":"#404cbf","border":{"width":0.005,"color":"#000000"}},{"type":"circle","center":{"x":0.53333333333333,"y":-0.016666666666667,"distance":0.53359368645274,"angle":-1.7899106082461},"radius":0.03,"color":"#bf404d","border":{"width":0.005,"color":"#000000"}},{"type":"circle","center":{"x":-0.30333333333333,"y":-0.44666666666667,"distance":0.53992797873626,"angle":-124.18060159802},"radius":0.03,"color":"#4cbf40","border":{"width":0.005,"color":"#000000"}},{"type":"circle","center":{"x":0.54,"y":-0.22666666666667,"distance":0.58564304638387,"angle":-22.770378908762},"radius":0.03,"color":"#404cbf","border":{"width":0.005,"color":"#000000"}},{"type":"circle","center":{"x":0.45333333333333,"y":0.033333333333333,"distance":0.45455717156615,"angle":4.2053570017086},"radius":0.03,"color":"#bf404d","border":{"width":0.005,"color":"#000000"}},{"type":"circle","center":{"x":-0.35,"y":-0.29333333333333,"distance":0.45666666666667,"angle":-140.0337869562},"radius":0.03,"color":"#4cbf40","border":{"width":0.005,"color":"#000000"}},{"type":"circle","center":{"x":-0.37666666666667,"y":-0.40333333333333,"distance":0.55186552307202,"angle":-133.04193257077},"radius":0.03,"color":"#404cbf","border":{"width":0.005,"color":"#000000"}},{"type":"circle","center":{"x":0.37666666666667,"y":0.22333333333333,"distance":0.43789902438297,"angle":30.66456458048},"radius":0.03,"color":"#bf404d","border":{"width":0.005,"color":"#000000"}},{"type":"circle","center":{"x":-0.47666666666667,"y":-0.093333333333333,"distance":0.48571825395204,"angle":-168.92140858178},"radius":0.03,"color":"#4cbf40","border":{"width":0.005,"color":"#000000"}},{"type":"circle","center":{"x":-0.38,"y":-0.18333333333333,"distance":0.42191362991863,"angle":-154.24472923983},"radius":0.03,"color":"#404cbf","border":{"width":0.005,"color":"#000000"}},{"type":"circle","center":{"x":0.38333333333333,"y":0.093333333333333,"distance":0.39453207164381,"angle":13.684019752248},"radius":0.03,"color":"#bf404d","border":{"width":0.005,"color":"#000000"}}],"state":{"nReported":15,"selected":null,"start":"2018-04-21T00:17:31.994Z","reporting":null,"displayTime":0},"stimuli":[{"type":"circle","center":{"x":0.63666666666667,"y":0.026666666666667,"distance":0.63722488617093,"angle":2.3984213340925},"radius":0.03,"color":"#4cbf40","border":{"width":0.005,"color":"#000000"}},{"type":"circle","center":{"x":0.58333333333333,"y":-0.04,"distance":0.58470315355553,"angle":-3.9227128905105},"radius":0.03,"color":"#404cbf","border":{"width":0.005,"color":"#000000"}},{"type":"circle","center":{"x":0.46,"y":-0.21,"distance":0.50566787519082,"angle":-24.537728476578},"radius":0.03,"color":"#bf404d","border":{"width":0.005,"color":"#000000"}},{"type":"circle","center":{"x":-0.25,"y":-0.51333333333333,"distance":0.57097382699307,"angle":-115.96668358978},"radius":0.03,"color":"#4cbf40","border":{"width":0.005,"color":"#000000"}},{"type":"circle","center":{"x":0.52666666666667,"y":-0.14333333333333,"distance":0.54582251897684,"angle":-15.224430018519},"radius":0.03,"color":"#404cbf","border":{"width":0.005,"color":"#000000"}},{"type":"circle","center":{"x":0.33333333333333,"y":-0.19333333333333,"distance":0.38534256044316,"angle":-30.113733150982},"radius":0.03,"color":"#bf404d","border":{"width":0.005,"color":"#000000"}},{"type":"circle","center":{"x":-0.37666666666667,"y":-0.41666666666667,"distance":0.56168397599441,"angle":-132.11358145614},"radius":0.03,"color":"#4cbf40","border":{"width":0.005,"color":"#000000"}},{"type":"circle","center":{"x":-0.34,"y":-0.46333333333333,"distance":0.57469798831889,"angle":-126.27170358642},"radius":0.03,"color":"#404cbf","border":{"width":0.005,"color":"#000000"}},{"type":"circle","center":{"x":0.17,"y":-0.1,"distance":0.19723082923316,"angle":-30.46554491946},"radius":0.03,"color":"#bf404d","border":{"width":0.005,"color":"#000000"}},{"type":"circle","center":{"x":-0.38666666666667,"y":-0.27333333333333,"distance":0.47352108952213,"angle":-144.74364128704},"radius":0.03,"color":"#4cbf40","border":{"width":0.005,"color":"#000000"}},{"type":"circle","center":{"x":-0.37333333333333,"y":-0.35333333333333,"distance":0.51402550736537,"angle":-136.57655005518},"radius":0.03,"color":"#404cbf","border":{"width":0.005,"color":"#000000"}},{"type":"circle","center":{"x":0.096666666666667,"y":0.036666666666667,"distance":0.10338708279514,"angle":20.772254682046},"radius":0.03,"color":"#bf404d","border":{"width":0.005,"color":"#000000"}},{"type":"circle","center":{"x":-0.54666666666667,"y":-0.15666666666667,"distance":0.56867291907465,"angle":-164.00847224148},"radius":0.03,"color":"#4cbf40","border":{"width":0.005,"color":"#000000"}},{"type":"circle","center":{"x":-0.46333333333333,"y":-0.19,"distance":0.5007771737787,"angle":-157.70284212321},"radius":0.03,"color":"#404cbf","border":{"width":0.005,"color":"#000000"}},{"type":"circle","center":{"x":0.023333333333333,"y":0.18666666666667,"distance":0.1881193474603,"angle":82.874983651098},"radius":0.03,"color":"#bf404d","border":{"width":0.005,"color":"#000000"}}],"seed":1,"chain":6,"iter":7,"settings":{"name":"live","maxTrials":10,"debug":false,"error_threshold":0.4,"error_match":"color","readURL":"request.php","saveURL":"submit.php","timing":{"consent":null,"instructions":null,"presentation":15000,"mask":1000,"response":null,"feedback":null},"default":{"n":15,"practice":[3,9],"colors":[0,0.333,0.666],"coffset":0.317,"type":"circle","environment":{"type":"circle","center":{"x":0,"y":0},"radius":0.95,"color":"#FFFFFF","border":{"width":0.01,"color":"#888888"}},"circle":{"type":"circle","center":{"x":null,"y":null},"radius":0.03,"color":"#333333","border":{"width":0.005,"color":"#000000"}},"response":{"xy":true,"angle":false,"color":false,"size":false,"aspect_ratio":false}}},"error":0.25175179906967,"score":37,"submit_time":"2018-04-20 17:18:47"}