{"trial_n":4,"sid":"A3AG7GG8ED8SDH","expt":"live","phase":"feedback","error_threshold":0.4,"responses":[{"type":"circle","center":{"x":0.37833333333333,"y":0.70333333333333,"distance":0.79863251179055,"angle":61.72353926272},"radius":0.03,"color":"#4cbf40","border":{"width":0.005,"color":"#000000"}},{"type":"circle","center":{"x":0.61833333333333,"y":0.28,"distance":0.67877544969681,"angle":24.362453015312},"radius":0.03,"color":"#404cbf","border":{"width":0.005,"color":"#000000"}},{"type":"circle","center":{"x":0.115,"y":0.6,"distance":0.61092143521078,"angle":79.149895370203},"radius":0.03,"color":"#bf404d","border":{"width":0.005,"color":"#000000"}},{"type":"circle","center":{"x":0.59166666666667,"y":0.026666666666667,"distance":0.59226730076508,"angle":2.5805985773887},"radius":0.03,"color":"#4cbf40","border":{"width":0.005,"color":"#000000"}},{"type":"circle","center":{"x":0.20833333333333,"y":-0.69666666666667,"distance":0.7271500685706,"angle":-73.351070378331},"radius":0.03,"color":"#404cbf","border":{"width":0.005,"color":"#000000"}},{"type":"circle","center":{"x":0.54166666666667,"y":-0.74,"distance":0.91706203594837,"angle":-53.796544468975},"radius":0.03,"color":"#bf404d","border":{"width":0.005,"color":"#000000"}},{"type":"circle","center":{"x":-0.46833333333333,"y":-0.11,"distance":0.48107807174211,"angle":-166.78221199376},"radius":0.03,"color":"#4cbf40","border":{"width":0.005,"color":"#000000"}},{"type":"circle","center":{"x":-0.28833333333333,"y":0.67,"distance":0.72940805528258,"angle":113.28454271367},"radius":0.03,"color":"#404cbf","border":{"width":0.005,"color":"#000000"}},{"type":"circle","center":{"x":0.25166666666667,"y":-0.53666666666667,"distance":0.59274549532006,"angle":-64.876048115044},"radius":0.03,"color":"#bf404d","border":{"width":0.005,"color":"#000000"}},{"type":"circle","center":{"x":0.46833333333333,"y":0.043333333333333,"distance":0.47033380581124,"angle":5.2863373619688},"radius":0.03,"color":"#4cbf40","border":{"width":0.005,"color":"#000000"}},{"type":"circle","center":{"x":-0.355,"y":0.61,"distance":0.70577971067466,"angle":120.19800191657},"radius":0.03,"color":"#404cbf","border":{"width":0.005,"color":"#000000"}},{"type":"circle","center":{"x":-0.20833333333333,"y":-0.23666666666667,"distance":0.31529968107959,"angle":-131.35687178779},"radius":0.03,"color":"#bf404d","border":{"width":0.005,"color":"#000000"}},{"type":"circle","center":{"x":-0.62833333333333,"y":-0.063333333333333,"distance":0.63151713269625,"angle":-174.24426839008},"radius":0.03,"color":"#4cbf40","border":{"width":0.005,"color":"#000000"}},{"type":"circle","center":{"x":0.185,"y":0.88333333333333,"distance":0.90249807632913,"angle":78.171286162834},"radius":0.03,"color":"#404cbf","border":{"width":0.005,"color":"#000000"}},{"type":"circle","center":{"x":-0.775,"y":0.12666666666667,"distance":0.78528303460882,"angle":170.7176011418},"radius":0.03,"color":"#bf404d","border":{"width":0.005,"color":"#000000"}}],"state":{"nReported":15,"selected":null,"start":"2018-04-21T00:07:15.951Z","reporting":null,"displayTime":0},"stimuli":[{"type":"circle","center":{"x":-0.48499351527753,"y":-0.068927983004569},"radius":0.03,"color":"#4cbf40","border":{"width":0.005,"color":"#000000"}},{"type":"circle","center":{"x":0.014380058168662,"y":0.8816083595665},"radius":0.03,"color":"#404cbf","border":{"width":0.005,"color":"#000000"}},{"type":"circle","center":{"x":-0.75847941748128,"y":0.19240749090973},"radius":0.03,"color":"#bf404d","border":{"width":0.005,"color":"#000000"}},{"type":"circle","center":{"x":0.45409307695427,"y":0.11297259733211},"radius":0.03,"color":"#4cbf40","border":{"width":0.005,"color":"#000000"}},{"type":"circle","center":{"x":-0.4821945088478,"y":0.56861164176659},"radius":0.03,"color":"#404cbf","border":{"width":0.005,"color":"#000000"}},{"type":"circle","center":{"x":0.65562003159292,"y":-0.62527588796779},"radius":0.03,"color":"#bf404d","border":{"width":0.005,"color":"#000000"}},{"type":"circle","center":{"x":0.26823767569503,"y":0.72139393103144},"radius":0.03,"color":"#4cbf40","border":{"width":0.005,"color":"#000000"}},{"type":"circle","center":{"x":0.316959162829,"y":-0.55904514881792},"radius":0.03,"color":"#404cbf","border":{"width":0.005,"color":"#000000"}},{"type":"circle","center":{"x":-0.20646365995438,"y":-0.15838009456826},"radius":0.03,"color":"#bf404d","border":{"width":0.005,"color":"#000000"}},{"type":"circle","center":{"x":-0.66214262390507,"y":0.010384683450971},"radius":0.03,"color":"#4cbf40","border":{"width":0.005,"color":"#000000"}},{"type":"circle","center":{"x":0.57378750330995,"y":0.3653036809245},"radius":0.03,"color":"#404cbf","border":{"width":0.005,"color":"#000000"}},{"type":"circle","center":{"x":0.34363802065789,"y":-0.43353118092994},"radius":0.03,"color":"#bf404d","border":{"width":0.005,"color":"#000000"}},{"type":"circle","center":{"x":0.58496891838197,"y":0.11102785682728},"radius":0.03,"color":"#4cbf40","border":{"width":0.005,"color":"#000000"}},{"type":"circle","center":{"x":-0.41945587626158,"y":0.61733185185246},"radius":0.03,"color":"#404cbf","border":{"width":0.005,"color":"#000000"}},{"type":"circle","center":{"x":-0.013485273792957,"y":0.69825960329524},"radius":0.03,"color":"#bf404d","border":{"width":0.005,"color":"#000000"}}],"seed":9,"chain":9,"iter":0,"settings":{"name":"live","maxTrials":10,"debug":false,"error_threshold":0.4,"error_match":"color","readURL":"request.php","saveURL":"submit.php","timing":{"consent":null,"instructions":null,"presentation":15000,"mask":1000,"response":null,"feedback":null},"default":{"n":15,"practice":[3,9],"colors":[0,0.333,0.666],"coffset":0.317,"type":"circle","environment":{"type":"circle","center":{"x":0,"y":0},"radius":0.95,"color":"#FFFFFF","border":{"width":0.01,"color":"#888888"}},"circle":{"type":"circle","center":{"x":null,"y":null},"radius":0.03,"color":"#333333","border":{"width":0.005,"color":"#000000"}},"response":{"xy":true,"angle":false,"color":false,"size":false,"aspect_ratio":false}}},"error":0.11451218901678,"score":71,"submit_time":"2018-04-20 17:09:03"}