{"trial_n":3,"sid":"A3AG7GG8ED8SDH","expt":"live","phase":"feedback","error_threshold":0.4,"responses":[{"type":"circle","center":{"x":0.48166666666667,"y":-0.47,"distance":0.67298051812647,"angle":-44.297635085117},"radius":0.03,"color":"#4cbf40","border":{"width":0.005,"color":"#000000"}},{"type":"circle","center":{"x":0.56833333333333,"y":0.32333333333333,"distance":0.65387095226981,"angle":29.636195155703},"radius":0.03,"color":"#404cbf","border":{"width":0.005,"color":"#000000"}},{"type":"circle","center":{"x":0.23166666666667,"y":0.08,"distance":0.24509068616421,"angle":19.051008731321},"radius":0.03,"color":"#bf404d","border":{"width":0.005,"color":"#000000"}},{"type":"circle","center":{"x":0.28166666666667,"y":-0.37,"distance":0.46501194727782,"angle":-52.719386955391},"radius":0.03,"color":"#4cbf40","border":{"width":0.005,"color":"#000000"}},{"type":"circle","center":{"x":0.75833333333333,"y":0.26333333333333,"distance":0.8027539404381,"angle":19.149698225564},"radius":0.03,"color":"#404cbf","border":{"width":0.005,"color":"#000000"}},{"type":"circle","center":{"x":0.088333333333333,"y":-0.24,"distance":0.25573966797855,"angle":-69.793581437044},"radius":0.03,"color":"#bf404d","border":{"width":0.005,"color":"#000000"}},{"type":"circle","center":{"x":-0.015,"y":-0.67666666666667,"distance":0.67683290240485,"angle":-91.269895506163},"radius":0.03,"color":"#4cbf40","border":{"width":0.005,"color":"#000000"}},{"type":"circle","center":{"x":0.675,"y":0.0033333333333333,"distance":0.6750082304025,"angle":0.28293982109407},"radius":0.03,"color":"#404cbf","border":{"width":0.005,"color":"#000000"}},{"type":"circle","center":{"x":-0.035,"y":-0.47333333333333,"distance":0.47462558342808,"angle":-94.22896343989},"radius":0.03,"color":"#bf404d","border":{"width":0.005,"color":"#000000"}},{"type":"circle","center":{"x":0.20166666666667,"y":-0.72666666666667,"distance":0.75413121463634,"angle":-74.489445321344},"radius":0.03,"color":"#4cbf40","border":{"width":0.005,"color":"#000000"}},{"type":"circle","center":{"x":0.445,"y":-0.046666666666667,"distance":0.44744025051148,"angle":-5.9866640676099},"radius":0.03,"color":"#404cbf","border":{"width":0.005,"color":"#000000"}},{"type":"circle","center":{"x":-0.22166666666667,"y":-0.10333333333333,"distance":0.24456878150919,"angle":-155.00669473774},"radius":0.03,"color":"#bf404d","border":{"width":0.005,"color":"#000000"}},{"type":"circle","center":{"x":-0.091666666666667,"y":-0.37333333333333,"distance":0.38442236609692,"angle":-103.79525317712},"radius":0.03,"color":"#4cbf40","border":{"width":0.005,"color":"#000000"}},{"type":"circle","center":{"x":0.57166666666667,"y":-0.25666666666667,"distance":0.6266422867598,"angle":-24.179107146689},"radius":0.03,"color":"#404cbf","border":{"width":0.005,"color":"#000000"}},{"type":"circle","center":{"x":-0.105,"y":0.10666666666667,"distance":0.14967557508751,"angle":134.54886145321},"radius":0.03,"color":"#bf404d","border":{"width":0.005,"color":"#000000"}}],"state":{"nReported":15,"selected":null,"start":"2018-04-21T00:23:28.384Z","reporting":null,"displayTime":0},"stimuli":[{"type":"circle","center":{"x":0.26333333333333,"y":-0.64,"distance":0.6920581221577,"angle":-67.634875631353},"radius":0.03,"color":"#4cbf40","border":{"width":0.005,"color":"#000000"}},{"type":"circle","center":{"x":0.25333333333333,"y":0.39666666666667,"distance":0.47066147305916,"angle":57.435441502528},"radius":0.03,"color":"#404cbf","border":{"width":0.005,"color":"#000000"}},{"type":"circle","center":{"x":-0.28333333333333,"y":0.05,"distance":0.2877112750272,"angle":169.99202019856},"radius":0.03,"color":"#bf404d","border":{"width":0.005,"color":"#000000"}},{"type":"circle","center":{"x":0.023333333333333,"y":-0.60666666666667,"distance":0.60711521879203,"angle":-87.797401838234},"radius":0.03,"color":"#4cbf40","border":{"width":0.005,"color":"#000000"}},{"type":"circle","center":{"x":0.22333333333333,"y":0.0033333333333333,"distance":0.22335820757001,"angle":0.85509739626672},"radius":0.03,"color":"#404cbf","border":{"width":0.005,"color":"#000000"}},{"type":"circle","center":{"x":0.033333333333333,"y":0.11,"distance":0.11493959766378,"angle":73.141601232262},"radius":0.03,"color":"#bf404d","border":{"width":0.005,"color":"#000000"}},{"type":"circle","center":{"x":0.36666666666667,"y":-0.40666666666667,"distance":0.54756024529016,"angle":-47.960936134164},"radius":0.03,"color":"#4cbf40","border":{"width":0.005,"color":"#000000"}},{"type":"circle","center":{"x":0.42666666666667,"y":0.056666666666667,"distance":0.43041323812768,"angle":7.5653210684323},"radius":0.03,"color":"#404cbf","border":{"width":0.005,"color":"#000000"}},{"type":"circle","center":{"x":-0.053333333333333,"y":-0.37,"distance":0.37382408221575,"angle":-98.202354244626},"radius":0.03,"color":"#bf404d","border":{"width":0.005,"color":"#000000"}},{"type":"circle","center":{"x":0.17,"y":-0.39,"distance":0.42544094772365,"angle":-66.447736327105},"radius":0.03,"color":"#4cbf40","border":{"width":0.005,"color":"#000000"}},{"type":"circle","center":{"x":0.48333333333333,"y":0.35,"distance":0.59675045966561,"angle":35.909723079178},"radius":0.03,"color":"#404cbf","border":{"width":0.005,"color":"#000000"}},{"type":"circle","center":{"x":-0.016666666666667,"y":-0.15666666666667,"distance":0.15755069730795,"angle":-96.072456407208},"radius":0.03,"color":"#bf404d","border":{"width":0.005,"color":"#000000"}},{"type":"circle","center":{"x":-0.13,"y":-0.33,"distance":0.35468295701936,"angle":-111.50143432405},"radius":0.03,"color":"#4cbf40","border":{"width":0.005,"color":"#000000"}},{"type":"circle","center":{"x":0.38666666666667,"y":-0.19666666666667,"distance":0.43380743295717,"angle":-26.958830403165},"radius":0.03,"color":"#404cbf","border":{"width":0.005,"color":"#000000"}},{"type":"circle","center":{"x":-0.33,"y":-0.15,"distance":0.36249137920784,"angle":-155.55604521958},"radius":0.03,"color":"#bf404d","border":{"width":0.005,"color":"#000000"}}],"seed":7,"chain":3,"iter":4,"settings":{"name":"live","maxTrials":10,"debug":false,"error_threshold":0.4,"error_match":"color","readURL":"request.php","saveURL":"submit.php","timing":{"consent":null,"instructions":null,"presentation":15000,"mask":1000,"response":null,"feedback":null},"default":{"n":15,"practice":[3,9],"colors":[0,0.333,0.666],"coffset":0.317,"type":"circle","environment":{"type":"circle","center":{"x":0,"y":0},"radius":0.95,"color":"#FFFFFF","border":{"width":0.01,"color":"#888888"}},"circle":{"type":"circle","center":{"x":null,"y":null},"radius":0.03,"color":"#333333","border":{"width":0.005,"color":"#000000"}},"response":{"xy":true,"angle":false,"color":false,"size":false,"aspect_ratio":false}}},"error":0.16803551523742,"score":58,"submit_time":"2018-04-20 17:24:58"}