{"trial_n":3,"sid":"APLF5MYVPQJNL","expt":"live","phase":"feedback","error_threshold":0.4,"responses":[{"type":"circle","center":{"x":0.19166666666667,"y":-0.14666666666667,"distance":0.24134461299607,"angle":-37.423845104311},"radius":0.03,"color":"#4cbf40","border":{"width":0.005,"color":"#000000"}},{"type":"circle","center":{"x":0.185,"y":0.023333333333333,"distance":0.1864656655914,"angle":7.1885371427366},"radius":0.03,"color":"#404cbf","border":{"width":0.005,"color":"#000000"}},{"type":"circle","center":{"x":-0.265,"y":0.066666666666667,"distance":0.2732571031912,"angle":165.87899952361},"radius":0.03,"color":"#bf404d","border":{"width":0.005,"color":"#000000"}},{"type":"circle","center":{"x":-0.325,"y":-0.48333333333333,"distance":0.58243979183355,"angle":-123.91743053697},"radius":0.03,"color":"#4cbf40","border":{"width":0.005,"color":"#000000"}},{"type":"circle","center":{"x":0.23166666666667,"y":-0.30666666666667,"distance":0.38433564613354,"angle":-52.931332017105},"radius":0.03,"color":"#404cbf","border":{"width":0.005,"color":"#000000"}},{"type":"circle","center":{"x":-0.12166666666667,"y":-0.16666666666667,"distance":0.20635056470859,"angle":-126.12944414324},"radius":0.03,"color":"#bf404d","border":{"width":0.005,"color":"#000000"}},{"type":"circle","center":{"x":0.051666666666667,"y":-0.13666666666667,"distance":0.14610688629295,"angle":-69.290962408351},"radius":0.03,"color":"#4cbf40","border":{"width":0.005,"color":"#000000"}},{"type":"circle","center":{"x":-0.12166666666667,"y":-0.05,"distance":0.1315400234825,"angle":-157.65935204001},"radius":0.03,"color":"#404cbf","border":{"width":0.005,"color":"#000000"}},{"type":"circle","center":{"x":-0.005,"y":0.053333333333333,"distance":0.053567195599961,"angle":95.355825042855},"radius":0.03,"color":"#bf404d","border":{"width":0.005,"color":"#000000"}},{"type":"circle","center":{"x":-0.565,"y":-0.25333333333333,"distance":0.61919526627533,"angle":-155.84960534377},"radius":0.03,"color":"#4cbf40","border":{"width":0.005,"color":"#000000"}},{"type":"circle","center":{"x":0.038333333333333,"y":-0.29,"distance":0.29252255373636,"angle":-82.470073222312},"radius":0.03,"color":"#404cbf","border":{"width":0.005,"color":"#000000"}},{"type":"circle","center":{"x":-0.47833333333333,"y":-0.15333333333333,"distance":0.50230855944219,"angle":-162.22635819437},"radius":0.03,"color":"#bf404d","border":{"width":0.005,"color":"#000000"}},{"type":"circle","center":{"x":-0.21166666666667,"y":-0.23333333333333,"distance":0.31503527139389,"angle":-132.21251915797},"radius":0.03,"color":"#4cbf40","border":{"width":0.005,"color":"#000000"}},{"type":"circle","center":{"x":-0.365,"y":-0.03,"distance":0.3662308015446,"angle":-175.3013194827},"radius":0.03,"color":"#404cbf","border":{"width":0.005,"color":"#000000"}},{"type":"circle","center":{"x":-0.29166666666667,"y":-0.12,"distance":0.31538776838115,"angle":-157.63633398453},"radius":0.03,"color":"#bf404d","border":{"width":0.005,"color":"#000000"}}],"state":{"nReported":15,"selected":null,"start":"2018-04-21T00:17:49.951Z","reporting":null,"displayTime":0},"stimuli":[{"type":"circle","center":{"x":0.41166666666667,"y":-0.10333333333333,"distance":0.42443753630213,"angle":-14.090810860488},"radius":0.03,"color":"#4cbf40","border":{"width":0.005,"color":"#000000"}},{"type":"circle","center":{"x":0.225,"y":-0.14333333333333,"distance":0.26677601924544,"angle":-32.49864594448},"radius":0.03,"color":"#404cbf","border":{"width":0.005,"color":"#000000"}},{"type":"circle","center":{"x":-0.23833333333333,"y":-0.36333333333333,"distance":0.43452720155232,"angle":-123.26340471422},"radius":0.03,"color":"#bf404d","border":{"width":0.005,"color":"#000000"}},{"type":"circle","center":{"x":-0.091666666666667,"y":0.5,"distance":0.50833333333333,"angle":100.38885781547},"radius":0.03,"color":"#4cbf40","border":{"width":0.005,"color":"#000000"}},{"type":"circle","center":{"x":-0.135,"y":-0.47666666666667,"distance":0.49541508970873,"angle":-105.81301217275},"radius":0.03,"color":"#404cbf","border":{"width":0.005,"color":"#000000"}},{"type":"circle","center":{"x":0.068333333333333,"y":-0.07,"distance":0.097823537272195,"angle":-45.690277197865},"radius":0.03,"color":"#bf404d","border":{"width":0.005,"color":"#000000"}},{"type":"circle","center":{"x":-0.058333333333333,"y":0,"distance":0.058333333333333,"angle":180},"radius":0.03,"color":"#4cbf40","border":{"width":0.005,"color":"#000000"}},{"type":"circle","center":{"x":0.061666666666667,"y":0.093333333333333,"distance":0.11186549463033,"angle":56.546690545927},"radius":0.03,"color":"#404cbf","border":{"width":0.005,"color":"#000000"}},{"type":"circle","center":{"x":0.335,"y":-0.32,"distance":0.46327637539594,"angle":-43.688112217496},"radius":0.03,"color":"#bf404d","border":{"width":0.005,"color":"#000000"}},{"type":"circle","center":{"x":-0.585,"y":-0.15666666666667,"distance":0.60561493083018,"angle":-165.00764069326},"radius":0.03,"color":"#4cbf40","border":{"width":0.005,"color":"#000000"}},{"type":"circle","center":{"x":-0.415,"y":0.033333333333333,"distance":0.41633653588307,"angle":175.40778798908},"radius":0.03,"color":"#404cbf","border":{"width":0.005,"color":"#000000"}},{"type":"circle","center":{"x":-0.49833333333333,"y":-0.086666666666667,"distance":0.50581342629691,"angle":-170.13419305692},"radius":0.03,"color":"#bf404d","border":{"width":0.005,"color":"#000000"}},{"type":"circle","center":{"x":-0.11833333333333,"y":-0.24333333333333,"distance":0.2705806513572,"angle":-115.93371827743},"radius":0.03,"color":"#4cbf40","border":{"width":0.005,"color":"#000000"}},{"type":"circle","center":{"x":-0.265,"y":-0.14,"distance":0.29970819141291,"angle":-152.15242174021},"radius":0.03,"color":"#404cbf","border":{"width":0.005,"color":"#000000"}},{"type":"circle","center":{"x":-0.315,"y":-0.01,"distance":0.31515869018639,"angle":-178.18169703555},"radius":0.03,"color":"#bf404d","border":{"width":0.005,"color":"#000000"}}],"seed":0,"chain":7,"iter":7,"settings":{"name":"live","maxTrials":10,"debug":false,"error_threshold":0.4,"error_match":"color","readURL":"request.php","saveURL":"submit.php","timing":{"consent":null,"instructions":null,"presentation":15000,"mask":1000,"response":null,"feedback":null},"default":{"n":15,"practice":[3,9],"colors":[0,0.333,0.666],"coffset":0.317,"type":"circle","environment":{"type":"circle","center":{"x":0,"y":0},"radius":0.95,"color":"#FFFFFF","border":{"width":0.01,"color":"#888888"}},"circle":{"type":"circle","center":{"x":null,"y":null},"radius":0.03,"color":"#333333","border":{"width":0.005,"color":"#000000"}},"response":{"xy":true,"angle":false,"color":false,"size":false,"aspect_ratio":false}}},"error":0.22690590348884,"score":43,"submit_time":"2018-04-20 17:18:49"}