{"trial_n":1,"sid":"A161AJDHLJVCLZ","expt":"practice","phase":"feedback","error_threshold":0.4,"responses":[{"type":"circle","center":{"x":0.5875,"y":-0.20989583333333,"distance":0.6238689853252,"angle":-19.660259255366},"radius":0.03,"color":"#4cbf40","border":{"width":0.005,"color":"#000000"}},{"type":"circle","center":{"x":0.25083333333333,"y":-0.1265625,"distance":0.28095449367711,"angle":-26.774054917472},"radius":0.03,"color":"#404cbf","border":{"width":0.005,"color":"#000000"}},{"type":"circle","center":{"x":0.66416666666667,"y":0.090104166666667,"distance":0.67025079034777,"angle":7.725863831695},"radius":0.03,"color":"#bf404d","border":{"width":0.005,"color":"#000000"}},{"type":"circle","center":{"x":0.27083333333333,"y":-0.3465625,"distance":0.43983662972824,"angle":-51.992913649517},"radius":0.03,"color":"#4cbf40","border":{"width":0.005,"color":"#000000"}},{"type":"circle","center":{"x":0.47083333333333,"y":0.5934375,"distance":0.75753025958309,"angle":51.571514585427},"radius":0.03,"color":"#404cbf","border":{"width":0.005,"color":"#000000"}},{"type":"circle","center":{"x":0.53083333333333,"y":-0.4465625,"distance":0.69368731730083,"angle":-40.072158517699},"radius":0.03,"color":"#bf404d","border":{"width":0.005,"color":"#000000"}},{"type":"circle","center":{"x":0.11083333333333,"y":0.076770833333333,"distance":0.13482502968096,"angle":34.709152011169},"radius":0.03,"color":"#4cbf40","border":{"width":0.005,"color":"#000000"}},{"type":"circle","center":{"x":-0.0525,"y":0.066770833333333,"distance":0.084938767262233,"angle":128.17695925621},"radius":0.03,"color":"#404cbf","border":{"width":0.005,"color":"#000000"}},{"type":"circle","center":{"x":-0.0058333333333333,"y":-0.13322916666667,"distance":0.13335680945671,"angle":-92.507049003144},"radius":0.03,"color":"#bf404d","border":{"width":0.005,"color":"#000000"}}],"state":{"nReported":9,"selected":null,"start":"2018-04-21T00:19:55.219Z","reporting":null,"displayTime":0},"stimuli":[{"type":"circle","center":{"x":-0.1240095354675,"y":0.098811234472846},"radius":0.03,"color":"#4cbf40","border":{"width":0.005,"color":"#000000"}},{"type":"circle","center":{"x":0.62778676568228,"y":0.47021237089868},"radius":0.03,"color":"#404cbf","border":{"width":0.005,"color":"#000000"}},{"type":"circle","center":{"x":0.32392404773953,"y":-0.72887401366827},"radius":0.03,"color":"#bf404d","border":{"width":0.005,"color":"#000000"}},{"type":"circle","center":{"x":0.55561584618868,"y":0.53902454448127},"radius":0.03,"color":"#4cbf40","border":{"width":0.005,"color":"#000000"}},{"type":"circle","center":{"x":0.042595604779932,"y":-0.37543184430055},"radius":0.03,"color":"#404cbf","border":{"width":0.005,"color":"#000000"}},{"type":"circle","center":{"x":0.75085508188226,"y":-0.1386612032584},"radius":0.03,"color":"#bf404d","border":{"width":0.005,"color":"#000000"}},{"type":"circle","center":{"x":0.28181278994228,"y":0.13004568993216},"radius":0.03,"color":"#4cbf40","border":{"width":0.005,"color":"#000000"}},{"type":"circle","center":{"x":0.32041957405488,"y":0.7061425303448},"radius":0.03,"color":"#404cbf","border":{"width":0.005,"color":"#000000"}},{"type":"circle","center":{"x":-0.18339096220111,"y":-0.12638444974843},"radius":0.03,"color":"#bf404d","border":{"width":0.005,"color":"#000000"}}],"seed":0,"chain":0,"iter":1,"settings":{"name":"live","maxTrials":10,"debug":false,"error_threshold":0.4,"error_match":"color","readURL":"request.php","saveURL":"submit.php","timing":{"consent":null,"instructions":null,"presentation":15000,"mask":1000,"response":null,"feedback":null},"default":{"n":15,"practice":[3,9],"colors":[0,0.333,0.666],"coffset":0.317,"type":"circle","environment":{"type":"circle","center":{"x":0,"y":0},"radius":0.95,"color":"#FFFFFF","border":{"width":0.01,"color":"#888888"}},"circle":{"type":"circle","center":{"x":null,"y":null},"radius":0.03,"color":"#333333","border":{"width":0.005,"color":"#000000"}},"response":{"xy":true,"angle":false,"color":false,"size":false,"aspect_ratio":false}}},"error":0.38875299191879,"score":3,"submit_time":"2018-04-20 17:20:44"}