{"expt":"live","seed":1,"chain":2,"iter":24,"stimuli":[{"type":"circle","center":{"x":0.445,"y":0.34,"distance":0.56002232098373,"angle":37.381453512431},"radius":0.03,"color":"#4cbf40","border":{"width":0.005,"color":"#000000"}},{"type":"circle","center":{"x":-0.15166666666667,"y":0.02,"distance":0.15297966458905,"angle":172.48785589695},"radius":0.03,"color":"#404cbf","border":{"width":0.005,"color":"#000000"}},{"type":"circle","center":{"x":-0.155,"y":0.74666666666667,"distance":0.76258515007251,"angle":101.72742540716},"radius":0.03,"color":"#bf404d","border":{"width":0.005,"color":"#000000"}},{"type":"circle","center":{"x":0.40166666666667,"y":0.16333333333333,"distance":0.43360568364459,"angle":22.128576691421},"radius":0.03,"color":"#4cbf40","border":{"width":0.005,"color":"#000000"}},{"type":"circle","center":{"x":0.14166666666667,"y":0.60333333333333,"distance":0.61974232996912,"angle":76.785948721448},"radius":0.03,"color":"#404cbf","border":{"width":0.005,"color":"#000000"}},{"type":"circle","center":{"x":-0.16166666666667,"y":0.56666666666667,"distance":0.5892768638104,"angle":105.92313646944},"radius":0.03,"color":"#bf404d","border":{"width":0.005,"color":"#000000"}},{"type":"circle","center":{"x":0.27833333333333,"y":0,"distance":0.27833333333333,"angle":0},"radius":0.03,"color":"#4cbf40","border":{"width":0.005,"color":"#000000"}},{"type":"circle","center":{"x":0.028333333333333,"y":0.48333333333333,"distance":0.48416308088173,"angle":86.645121260713},"radius":0.03,"color":"#404cbf","border":{"width":0.005,"color":"#000000"}},{"type":"circle","center":{"x":-0.19833333333333,"y":0.41,"distance":0.45545154639227,"angle":115.81490380298},"radius":0.03,"color":"#bf404d","border":{"width":0.005,"color":"#000000"}},{"type":"circle","center":{"x":0.10833333333333,"y":0,"distance":0.10833333333333,"angle":0},"radius":0.03,"color":"#4cbf40","border":{"width":0.005,"color":"#000000"}},{"type":"circle","center":{"x":-0.065,"y":0.31,"distance":0.31674121929424,"angle":101.84207611533},"radius":0.03,"color":"#404cbf","border":{"width":0.005,"color":"#000000"}},{"type":"circle","center":{"x":-0.295,"y":0.27333333333333,"distance":0.40216428373379,"angle":137.18323930018},"radius":0.03,"color":"#bf404d","border":{"width":0.005,"color":"#000000"}},{"type":"circle","center":{"x":-0.025,"y":0.11666666666667,"distance":0.1193151755273,"angle":102.09475707701},"radius":0.03,"color":"#4cbf40","border":{"width":0.005,"color":"#000000"}},{"type":"circle","center":{"x":-0.155,"y":0.14666666666667,"distance":0.21339191903892,"angle":136.58235392262},"radius":0.03,"color":"#404cbf","border":{"width":0.005,"color":"#000000"}},{"type":"circle","center":{"x":-0.37833333333333,"y":0.15666666666667,"distance":0.40948816290041,"angle":157.50570481228},"radius":0.03,"color":"#bf404d","border":{"width":0.005,"color":"#000000"}}]}