{"expt":"live","seed":4,"chain":1,"iter":2,"stimuli":[{"type":"circle","center":{"x":0.091666666666667,"y":0.26,"distance":0.27568601302529,"angle":70.579179047533},"radius":0.03,"color":"#4cbf40","border":{"width":0.005,"color":"#000000"}},{"type":"circle","center":{"x":-0.005,"y":0.1,"distance":0.1001249219725,"angle":92.862405226112},"radius":0.03,"color":"#404cbf","border":{"width":0.005,"color":"#000000"}},{"type":"circle","center":{"x":-0.20833333333333,"y":-0.12666666666667,"distance":0.24381801045497,"angle":-148.70039866537},"radius":0.03,"color":"#bf404d","border":{"width":0.005,"color":"#000000"}},{"type":"circle","center":{"x":0.10166666666667,"y":0.043333333333333,"distance":0.110516464334,"angle":23.085133672808},"radius":0.03,"color":"#4cbf40","border":{"width":0.005,"color":"#000000"}},{"type":"circle","center":{"x":0.24166666666667,"y":-0.52333333333333,"distance":0.57643781586183,"angle":-65.213289201214},"radius":0.03,"color":"#404cbf","border":{"width":0.005,"color":"#000000"}},{"type":"circle","center":{"x":0.34166666666667,"y":-0.41666666666667,"distance":0.53883877201091,"angle":-50.648247373735},"radius":0.03,"color":"#bf404d","border":{"width":0.005,"color":"#000000"}},{"type":"circle","center":{"x":0.33833333333333,"y":-0.16,"distance":0.37425852621476,"angle":-25.309766851626},"radius":0.03,"color":"#4cbf40","border":{"width":0.005,"color":"#000000"}},{"type":"circle","center":{"x":-0.038333333333333,"y":-0.30666666666667,"distance":0.30905321368478,"angle":-97.125016348902},"radius":0.03,"color":"#404cbf","border":{"width":0.005,"color":"#000000"}},{"type":"circle","center":{"x":0.165,"y":-0.37333333333333,"distance":0.40817003537469,"angle":-66.156283200884},"radius":0.03,"color":"#bf404d","border":{"width":0.005,"color":"#000000"}},{"type":"circle","center":{"x":0.091666666666667,"y":0.76,"distance":0.76550818269812,"angle":83.122546915288},"radius":0.03,"color":"#4cbf40","border":{"width":0.005,"color":"#000000"}},{"type":"circle","center":{"x":-0.078333333333333,"y":-0.52333333333333,"distance":0.5291633858166,"angle":-98.512919237838},"radius":0.03,"color":"#404cbf","border":{"width":0.005,"color":"#000000"}},{"type":"circle","center":{"x":-0.40166666666667,"y":-0.12666666666667,"distance":0.42116571032737,"angle":-162.49719062389},"radius":0.03,"color":"#bf404d","border":{"width":0.005,"color":"#000000"}},{"type":"circle","center":{"x":0.575,"y":-0.56,"distance":0.80263628126319,"angle":-44.242831134941},"radius":0.03,"color":"#4cbf40","border":{"width":0.005,"color":"#000000"}},{"type":"circle","center":{"x":-0.078333333333333,"y":-0.74,"distance":0.74413447112139,"angle":-96.042590818544},"radius":0.03,"color":"#404cbf","border":{"width":0.005,"color":"#000000"}},{"type":"circle","center":{"x":-0.655,"y":-0.053333333333333,"distance":0.65716774452528,"angle":-175.34496433245},"radius":0.03,"color":"#bf404d","border":{"width":0.005,"color":"#000000"}}]}