{"expt":"live","seed":1,"chain":4,"iter":13,"stimuli":[{"type":"circle","center":{"x":0.45166666666667,"y":-0.02,"distance":0.45210925424921,"angle":-2.5354262344655},"radius":0.03,"color":"#4cbf40","border":{"width":0.005,"color":"#000000"}},{"type":"circle","center":{"x":0.365,"y":0.24,"distance":0.43683520920365,"angle":33.326289687115},"radius":0.03,"color":"#404cbf","border":{"width":0.005,"color":"#000000"}},{"type":"circle","center":{"x":0.77833333333333,"y":0.17666666666667,"distance":0.79813149849438,"angle":12.788356463832},"radius":0.03,"color":"#bf404d","border":{"width":0.005,"color":"#000000"}},{"type":"circle","center":{"x":0.18166666666667,"y":-0.033333333333333,"distance":0.1846994555728,"angle":-10.397333522436},"radius":0.03,"color":"#4cbf40","border":{"width":0.005,"color":"#000000"}},{"type":"circle","center":{"x":0.078333333333333,"y":0.34333333333333,"distance":0.35215605757801,"angle":77.147656933609},"radius":0.03,"color":"#404cbf","border":{"width":0.005,"color":"#000000"}},{"type":"circle","center":{"x":0.395,"y":0.41333333333333,"distance":0.57172497273116,"angle":46.299269155204},"radius":0.03,"color":"#bf404d","border":{"width":0.005,"color":"#000000"}},{"type":"circle","center":{"x":-0.075,"y":0.016666666666667,"distance":0.076829537144107,"angle":167.47119229085},"radius":0.03,"color":"#4cbf40","border":{"width":0.005,"color":"#000000"}},{"type":"circle","center":{"x":-0.031666666666667,"y":0.56666666666667,"distance":0.56755078089004,"angle":93.198496279658},"radius":0.03,"color":"#404cbf","border":{"width":0.005,"color":"#000000"}},{"type":"circle","center":{"x":0.57833333333333,"y":0.33,"distance":0.66585992854687,"angle":29.709304909392},"radius":0.03,"color":"#bf404d","border":{"width":0.005,"color":"#000000"}},{"type":"circle","center":{"x":-0.35833333333333,"y":0.13,"distance":0.38118601466709,"angle":160.05969943167},"radius":0.03,"color":"#4cbf40","border":{"width":0.005,"color":"#000000"}},{"type":"circle","center":{"x":-0.17833333333333,"y":0.31666666666667,"distance":0.36342888651778,"angle":119.38637996035},"radius":0.03,"color":"#404cbf","border":{"width":0.005,"color":"#000000"}},{"type":"circle","center":{"x":0.21166666666667,"y":0.5,"distance":0.54295743643289,"angle":67.05543989543},"radius":0.03,"color":"#bf404d","border":{"width":0.005,"color":"#000000"}},{"type":"circle","center":{"x":-0.58833333333333,"y":0.22333333333333,"distance":0.62929634425197,"angle":159.21306789205},"radius":0.03,"color":"#4cbf40","border":{"width":0.005,"color":"#000000"}},{"type":"circle","center":{"x":-0.41833333333333,"y":0.38333333333333,"distance":0.56740393215259,"angle":137.49989138806},"radius":0.03,"color":"#404cbf","border":{"width":0.005,"color":"#000000"}},{"type":"circle","center":{"x":-0.285,"y":0.64666666666667,"distance":0.70668435512453,"angle":113.78412625245},"radius":0.03,"color":"#bf404d","border":{"width":0.005,"color":"#000000"}}]}