{"expt":"live","seed":6,"chain":9,"iter":2,"stimuli":[{"type":"circle","center":{"x":0.62166666666667,"y":0.29333333333333,"distance":0.68739645684924,"angle":25.260275287398},"radius":0.03,"color":"#4cbf40","border":{"width":0.005,"color":"#000000"}},{"type":"circle","center":{"x":0.36166666666667,"y":0.51333333333333,"distance":0.62794417657057,"angle":54.833563964207},"radius":0.03,"color":"#404cbf","border":{"width":0.005,"color":"#000000"}},{"type":"circle","center":{"x":-0.20166666666667,"y":-0.53,"distance":0.56707093422644,"angle":-110.83197735298},"radius":0.03,"color":"#bf404d","border":{"width":0.005,"color":"#000000"}},{"type":"circle","center":{"x":-0.50833333333333,"y":0.42333333333333,"distance":0.66152391407181,"angle":140.21291141661},"radius":0.03,"color":"#4cbf40","border":{"width":0.005,"color":"#000000"}},{"type":"circle","center":{"x":0.16833333333333,"y":0.34333333333333,"distance":0.38237924746106,"angle":63.881690486937},"radius":0.03,"color":"#404cbf","border":{"width":0.005,"color":"#000000"}},{"type":"circle","center":{"x":-0.35833333333333,"y":-0.53,"distance":0.6397677529993,"angle":-124.06265043574},"radius":0.03,"color":"#bf404d","border":{"width":0.005,"color":"#000000"}},{"type":"circle","center":{"x":-0.345,"y":-0.013333333333333,"distance":0.34525755281786,"angle":-177.7867718236},"radius":0.03,"color":"#4cbf40","border":{"width":0.005,"color":"#000000"}},{"type":"circle","center":{"x":0.74166666666667,"y":-0.28666666666667,"distance":0.79513975012083,"angle":-21.132357225415},"radius":0.03,"color":"#404cbf","border":{"width":0.005,"color":"#000000"}},{"type":"circle","center":{"x":-0.29833333333333,"y":-0.23666666666667,"distance":0.38080689186107,"angle":-141.57516970197},"radius":0.03,"color":"#bf404d","border":{"width":0.005,"color":"#000000"}},{"type":"circle","center":{"x":0.435,"y":-0.63666666666667,"distance":0.77108329280594,"angle":-55.657310932793},"radius":0.03,"color":"#4cbf40","border":{"width":0.005,"color":"#000000"}},{"type":"circle","center":{"x":-0.24166666666667,"y":-0.70333333333333,"distance":0.7436938587588,"angle":-108.96281846096},"radius":0.03,"color":"#404cbf","border":{"width":0.005,"color":"#000000"}},{"type":"circle","center":{"x":-0.48166666666667,"y":-0.20666666666667,"distance":0.52413155685275,"angle":-156.77748640653},"radius":0.03,"color":"#bf404d","border":{"width":0.005,"color":"#000000"}},{"type":"circle","center":{"x":-0.105,"y":-0.19,"distance":0.21708293346092,"angle":-118.92642583525},"radius":0.03,"color":"#4cbf40","border":{"width":0.005,"color":"#000000"}},{"type":"circle","center":{"x":-0.42166666666667,"y":-0.39,"distance":0.57437163733751,"angle":-137.23422582645},"radius":0.03,"color":"#404cbf","border":{"width":0.005,"color":"#000000"}},{"type":"circle","center":{"x":-0.445,"y":0.62333333333333,"distance":0.7658782177634,"angle":125.52318353994},"radius":0.03,"color":"#bf404d","border":{"width":0.005,"color":"#000000"}}]}