{"expt":"live","seed":8,"chain":2,"iter":2,"stimuli":[{"type":"circle","center":{"x":-0.47666666666667,"y":-0.3,"distance":0.56321497770488,"angle":-147.81489410811},"radius":0.03,"color":"#4cbf40","border":{"width":0.005,"color":"#000000"}},{"type":"circle","center":{"x":-0.086666666666667,"y":-0.76333333333333,"distance":0.76823752114101,"angle":-96.477459761942},"radius":0.03,"color":"#404cbf","border":{"width":0.005,"color":"#000000"}},{"type":"circle","center":{"x":-0.32,"y":-0.72,"distance":0.78790862414369,"angle":-113.96248897458},"radius":0.03,"color":"#bf404d","border":{"width":0.005,"color":"#000000"}},{"type":"circle","center":{"x":-0.72,"y":-0.1,"distance":0.72691127381545,"angle":-172.09283729704},"radius":0.03,"color":"#4cbf40","border":{"width":0.005,"color":"#000000"}},{"type":"circle","center":{"x":-0.09,"y":-0.39333333333333,"distance":0.40349858873497,"angle":-102.88818512577},"radius":0.03,"color":"#404cbf","border":{"width":0.005,"color":"#000000"}},{"type":"circle","center":{"x":0.01,"y":-0.61666666666667,"distance":0.61674774241806,"angle":-89.070960680578},"radius":0.03,"color":"#bf404d","border":{"width":0.005,"color":"#000000"}},{"type":"circle","center":{"x":-0.78,"y":0.30666666666667,"distance":0.83811958839085,"angle":158.53711407528},"radius":0.03,"color":"#4cbf40","border":{"width":0.005,"color":"#000000"}},{"type":"circle","center":{"x":-0.38666666666667,"y":-0.023333333333333,"distance":0.38737004989487,"angle":-176.54668374947},"radius":0.03,"color":"#404cbf","border":{"width":0.005,"color":"#000000"}},{"type":"circle","center":{"x":-0.28333333333333,"y":-0.46333333333333,"distance":0.5430981085914,"angle":-121.44623590227},"radius":0.03,"color":"#bf404d","border":{"width":0.005,"color":"#000000"}},{"type":"circle","center":{"x":0.29333333333333,"y":0.56,"distance":0.63217437819358,"angle":62.354024636261},"radius":0.03,"color":"#4cbf40","border":{"width":0.005,"color":"#000000"}},{"type":"circle","center":{"x":0.58333333333333,"y":0.14,"distance":0.59989813950185,"angle":13.495733280796},"radius":0.03,"color":"#404cbf","border":{"width":0.005,"color":"#000000"}},{"type":"circle","center":{"x":0.39,"y":0.63333333333333,"distance":0.74378162864588,"angle":58.375675740285},"radius":0.03,"color":"#bf404d","border":{"width":0.005,"color":"#000000"}},{"type":"circle","center":{"x":0.75333333333333,"y":0.24333333333333,"distance":0.79165789468824,"angle":17.90091574397},"radius":0.03,"color":"#4cbf40","border":{"width":0.005,"color":"#000000"}},{"type":"circle","center":{"x":-0.36,"y":0.27,"distance":0.45,"angle":143.13010235416},"radius":0.03,"color":"#404cbf","border":{"width":0.005,"color":"#000000"}},{"type":"circle","center":{"x":-0.63333333333333,"y":-0.45666666666667,"distance":0.78080442849382,"angle":-144.2064122395},"radius":0.03,"color":"#bf404d","border":{"width":0.005,"color":"#000000"}}]}