{"expt":"live","seed":2,"chain":0,"iter":15,"stimuli":[{"type":"circle","center":{"x":0.155,"y":-0.11,"distance":0.19006577808748,"angle":-35.362461887069},"radius":0.03,"color":"#4cbf40","border":{"width":0.005,"color":"#000000"}},{"type":"circle","center":{"x":-0.12166666666667,"y":0.39,"distance":0.4085373639923,"angle":107.32613669516},"radius":0.03,"color":"#404cbf","border":{"width":0.005,"color":"#000000"}},{"type":"circle","center":{"x":-0.18833333333333,"y":0.19666666666667,"distance":0.27229987554573,"angle":133.76002523369},"radius":0.03,"color":"#bf404d","border":{"width":0.005,"color":"#000000"}},{"type":"circle","center":{"x":0.23833333333333,"y":0.76,"distance":0.7964940538245,"angle":72.588758276766},"radius":0.03,"color":"#4cbf40","border":{"width":0.005,"color":"#000000"}},{"type":"circle","center":{"x":-0.34166666666667,"y":0.31333333333333,"distance":0.46358805947618,"angle":137.47689926065},"radius":0.03,"color":"#404cbf","border":{"width":0.005,"color":"#000000"}},{"type":"circle","center":{"x":-0.415,"y":0.15,"distance":0.44127655727446,"angle":160.12782418076},"radius":0.03,"color":"#bf404d","border":{"width":0.005,"color":"#000000"}},{"type":"circle","center":{"x":0.185,"y":0.56,"distance":0.58976690310664,"angle":71.718658797027},"radius":0.03,"color":"#4cbf40","border":{"width":0.005,"color":"#000000"}},{"type":"circle","center":{"x":0.40833333333333,"y":0.58333333333333,"distance":0.71204907758447,"angle":55.007979801441},"radius":0.03,"color":"#404cbf","border":{"width":0.005,"color":"#000000"}},{"type":"circle","center":{"x":0.50833333333333,"y":0.32333333333333,"distance":0.60245101230077,"angle":32.459035325295},"radius":0.03,"color":"#bf404d","border":{"width":0.005,"color":"#000000"}},{"type":"circle","center":{"x":0.10166666666667,"y":0.36333333333333,"distance":0.37728930838578,"angle":74.367502696945},"radius":0.03,"color":"#4cbf40","border":{"width":0.005,"color":"#000000"}},{"type":"circle","center":{"x":0.35833333333333,"y":0.41666666666667,"distance":0.54955790312658,"angle":49.304468960508},"radius":0.03,"color":"#404cbf","border":{"width":0.005,"color":"#000000"}},{"type":"circle","center":{"x":0.575,"y":0.51333333333333,"distance":0.77080225162561,"angle":41.756999255773},"radius":0.03,"color":"#bf404d","border":{"width":0.005,"color":"#000000"}},{"type":"circle","center":{"x":-0.038333333333333,"y":0.0033333333333333,"distance":0.038477987935384,"angle":175.03025927189},"radius":0.03,"color":"#4cbf40","border":{"width":0.005,"color":"#000000"}},{"type":"circle","center":{"x":0.27166666666667,"y":0.27666666666667,"distance":0.38774633747106,"angle":45.522439436959},"radius":0.03,"color":"#404cbf","border":{"width":0.005,"color":"#000000"}},{"type":"circle","center":{"x":0.37833333333333,"y":0.16,"distance":0.41077501276381,"angle":22.923865919177},"radius":0.03,"color":"#bf404d","border":{"width":0.005,"color":"#000000"}}]}