{"expt":"live","seed":0,"chain":6,"iter":4,"stimuli":[{"type":"circle","center":{"x":-0.33,"y":-0.39666666666667,"distance":0.51598880263475,"angle":-129.75818005302},"radius":0.03,"color":"#4cbf40","border":{"width":0.005,"color":"#000000"}},{"type":"circle","center":{"x":-0.07,"y":-0.043333333333333,"distance":0.082327260234856,"angle":-148.24051991519},"radius":0.03,"color":"#404cbf","border":{"width":0.005,"color":"#000000"}},{"type":"circle","center":{"x":0.41,"y":0.51333333333333,"distance":0.65697116459637,"angle":51.385592512567},"radius":0.03,"color":"#bf404d","border":{"width":0.005,"color":"#000000"}},{"type":"circle","center":{"x":-0.42333333333333,"y":0.28,"distance":0.50755404747781,"angle":146.51865934488},"radius":0.03,"color":"#4cbf40","border":{"width":0.005,"color":"#000000"}},{"type":"circle","center":{"x":0.10333333333333,"y":0.29666666666667,"distance":0.31414787742222,"angle":70.7960264945},"radius":0.03,"color":"#404cbf","border":{"width":0.005,"color":"#000000"}},{"type":"circle","center":{"x":-0.50333333333333,"y":-0.026666666666667,"distance":0.50403924009501,"angle":-176.96729738382},"radius":0.03,"color":"#bf404d","border":{"width":0.005,"color":"#000000"}},{"type":"circle","center":{"x":0.62,"y":-0.10333333333333,"distance":0.62855212813082,"angle":-9.4623222080256},"radius":0.03,"color":"#4cbf40","border":{"width":0.005,"color":"#000000"}},{"type":"circle","center":{"x":0.58333333333333,"y":0.11333333333333,"distance":0.59424087895585,"angle":10.994777349292},"radius":0.03,"color":"#404cbf","border":{"width":0.005,"color":"#000000"}},{"type":"circle","center":{"x":0.61333333333333,"y":0.26333333333333,"distance":0.66747451054121,"angle":23.236161511223},"radius":0.03,"color":"#bf404d","border":{"width":0.005,"color":"#000000"}},{"type":"circle","center":{"x":0.45666666666667,"y":-0.35,"distance":0.57536461869361,"angle":-37.467398599053},"radius":0.03,"color":"#4cbf40","border":{"width":0.005,"color":"#000000"}},{"type":"circle","center":{"x":-0.25,"y":0.61333333333333,"distance":0.66232754568852,"angle":112.17623634149},"radius":0.03,"color":"#404cbf","border":{"width":0.005,"color":"#000000"}},{"type":"circle","center":{"x":0.38333333333333,"y":0.32666666666667,"distance":0.50364228928432,"angle":40.436770245762},"radius":0.03,"color":"#bf404d","border":{"width":0.005,"color":"#000000"}},{"type":"circle","center":{"x":0.33666666666667,"y":-0.08,"distance":0.34604110224718,"angle":-13.366930696317},"radius":0.03,"color":"#4cbf40","border":{"width":0.005,"color":"#000000"}},{"type":"circle","center":{"x":0.13,"y":0.64333333333333,"distance":0.65633663449314,"angle":78.575932657999},"radius":0.03,"color":"#404cbf","border":{"width":0.005,"color":"#000000"}},{"type":"circle","center":{"x":0.27666666666667,"y":0.53333333333333,"distance":0.60082350893494,"angle":62.58197294254},"radius":0.03,"color":"#bf404d","border":{"width":0.005,"color":"#000000"}}]}